{
  "info": {
    "name": "InteliWallet API",
    "description": "Collection completa da API InteliWallet - Sistema de Carteira Financeira Gamificada",
    "schema": "https://schema.getpostman.com/json/collection/v2.1.0/collection.json",
    "_exporter_id": "inteliwallet"
  },
  "auth": {
    "type": "bearer",
    "bearer": [
      {
        "key": "token",
        "value": "{{jwt_token}}",
        "type": "string"
      }
    ]
  },
  "variable": [
    {
      "key": "base_url",
      "value": "http://localhost:3001/api",
      "type": "string"
    },
    {
      "key": "jwt_token",
      "value": "",
      "type": "string"
    },
    {
      "key": "user_id",
      "value": "",
      "type": "string"
    }
  ],
  "item": [
    {
      "name": "Authentication",
      "item": [
        {
          "name": "Register",
          "event": [
            {
              "listen": "test",
              "script": {
                "exec": [
                  "if (pm.response.code === 200) {",
                  "    var jsonData = pm.response.json();",
                  "    pm.collectionVariables.set(\"jwt_token\", jsonData.token);",
                  "    pm.collectionVariables.set(\"user_id\", jsonData.user.id);",
                  "    console.log(\"Token saved: \" + jsonData.token);",
                  "}"
                ]
              }
            }
          ],
          "request": {
            "auth": {
              "type": "noauth"
            },
            "method": "POST",
            "header": [
              {
                "key": "Content-Type",
                "value": "application/json"
              }
            ],
            "body": {
              "mode": "raw",
              "raw": "{\n  \"username\": \"joaosilva\",\n  \"email\": \"joao@example.com\",\n  \"password\": \"senha123\"\n}"
            },
            "url": {
              "raw": "{{base_url}}/auth/register",
              "host": ["{{base_url}}"],
              "path": ["auth", "register"]
            },
            "description": "Registra um novo usu치rio no sistema"
          },
          "response": []
        },
        {
          "name": "Login",
          "event": [
            {
              "listen": "test",
              "script": {
                "exec": [
                  "if (pm.response.code === 200) {",
                  "    var jsonData = pm.response.json();",
                  "    pm.collectionVariables.set(\"jwt_token\", jsonData.token);",
                  "    pm.collectionVariables.set(\"user_id\", jsonData.user.id);",
                  "    console.log(\"Token saved: \" + jsonData.token);",
                  "}"
                ]
              }
            }
          ],
          "request": {
            "auth": {
              "type": "noauth"
            },
            "method": "POST",
            "header": [
              {
                "key": "Content-Type",
                "value": "application/json"
              }
            ],
            "body": {
              "mode": "raw",
              "raw": "{\n  \"email\": \"joao@example.com\",\n  \"password\": \"senha123\"\n}"
            },
            "url": {
              "raw": "{{base_url}}/auth/login",
              "host": ["{{base_url}}"],
              "path": ["auth", "login"]
            },
            "description": "Autentica um usu치rio e retorna JWT token"
          },
          "response": []
        },
        {
          "name": "Get Me",
          "request": {
            "method": "GET",
            "header": [],
            "url": {
              "raw": "{{base_url}}/auth/me",
              "host": ["{{base_url}}"],
              "path": ["auth", "me"]
            },
            "description": "Retorna dados do usu치rio autenticado"
          },
          "response": []
        },
        {
          "name": "Logout",
          "request": {
            "method": "POST",
            "header": [],
            "url": {
              "raw": "{{base_url}}/auth/logout",
              "host": ["{{base_url}}"],
              "path": ["auth", "logout"]
            },
            "description": "Logout (stateless - token removido no client)"
          },
          "response": []
        }
      ]
    },
    {
      "name": "Users",
      "item": [
        {
          "name": "Get Profile",
          "request": {
            "method": "GET",
            "header": [],
            "url": {
              "raw": "{{base_url}}/users/profile",
              "host": ["{{base_url}}"],
              "path": ["users", "profile"]
            },
            "description": "Retorna perfil do usu치rio autenticado"
          },
          "response": []
        },
        {
          "name": "Update Profile",
          "request": {
            "method": "PUT",
            "header": [
              {
                "key": "Content-Type",
                "value": "application/json"
              }
            ],
            "body": {
              "mode": "raw",
              "raw": "{\n  \"username\": \"joaosilva_updated\",\n  \"avatar\": \"游땙\",\n  \"hasCompletedOnboarding\": true\n}"
            },
            "url": {
              "raw": "{{base_url}}/users/profile",
              "host": ["{{base_url}}"],
              "path": ["users", "profile"]
            },
            "description": "Atualiza perfil do usu치rio (todos os campos s칚o opcionais)"
          },
          "response": []
        },
        {
          "name": "Delete Account",
          "request": {
            "method": "DELETE",
            "header": [],
            "url": {
              "raw": "{{base_url}}/users/profile",
              "host": ["{{base_url}}"],
              "path": ["users", "profile"]
            },
            "description": "Deleta conta do usu치rio (cascade delete)"
          },
          "response": []
        }
      ]
    },
    {
      "name": "Transactions",
      "item": [
        {
          "name": "List Transactions",
          "request": {
            "method": "GET",
            "header": [],
            "url": {
              "raw": "{{base_url}}/transactions",
              "host": ["{{base_url}}"],
              "path": ["transactions"]
            },
            "description": "Lista todas as transa칞칫es do usu치rio"
          },
          "response": []
        },
        {
          "name": "Get Transaction",
          "request": {
            "method": "GET",
            "header": [],
            "url": {
              "raw": "{{base_url}}/transactions/:id",
              "host": ["{{base_url}}"],
              "path": ["transactions", ":id"],
              "variable": [
                {
                  "key": "id",
                  "value": "{{transaction_id}}"
                }
              ]
            },
            "description": "Retorna uma transa칞칚o espec칤fica"
          },
          "response": []
        },
        {
          "name": "Create Transaction (Income)",
          "event": [
            {
              "listen": "test",
              "script": {
                "exec": [
                  "if (pm.response.code === 200) {",
                  "    var jsonData = pm.response.json();",
                  "    pm.collectionVariables.set(\"transaction_id\", jsonData.id);",
                  "}"
                ]
              }
            }
          ],
          "request": {
            "method": "POST",
            "header": [
              {
                "key": "Content-Type",
                "value": "application/json"
              }
            ],
            "body": {
              "mode": "raw",
              "raw": "{\n  \"type\": \"income\",\n  \"amount\": 5000.00,\n  \"title\": \"Sal치rio\",\n  \"category\": \"Trabalho\",\n  \"date\": \"2025-10-24T15:00:00.000Z\"\n}"
            },
            "url": {
              "raw": "{{base_url}}/transactions",
              "host": ["{{base_url}}"],
              "path": ["transactions"]
            },
            "description": "Cria uma transa칞칚o de entrada (receita)"
          },
          "response": []
        },
        {
          "name": "Create Transaction (Expense)",
          "request": {
            "method": "POST",
            "header": [
              {
                "key": "Content-Type",
                "value": "application/json"
              }
            ],
            "body": {
              "mode": "raw",
              "raw": "{\n  \"type\": \"expense\",\n  \"amount\": 150.00,\n  \"title\": \"Compras no mercado\",\n  \"category\": \"Alimenta칞칚o\",\n  \"date\": \"2025-10-24T18:30:00.000Z\"\n}"
            },
            "url": {
              "raw": "{{base_url}}/transactions",
              "host": ["{{base_url}}"],
              "path": ["transactions"]
            },
            "description": "Cria uma transa칞칚o de sa칤da (despesa)"
          },
          "response": []
        },
        {
          "name": "Update Transaction",
          "request": {
            "method": "PUT",
            "header": [
              {
                "key": "Content-Type",
                "value": "application/json"
              }
            ],
            "body": {
              "mode": "raw",
              "raw": "{\n  \"title\": \"Compras no mercado (atualizado)\",\n  \"amount\": 175.50,\n  \"category\": \"Alimenta칞칚o\"\n}"
            },
            "url": {
              "raw": "{{base_url}}/transactions/:id",
              "host": ["{{base_url}}"],
              "path": ["transactions", ":id"],
              "variable": [
                {
                  "key": "id",
                  "value": "{{transaction_id}}"
                }
              ]
            },
            "description": "Atualiza uma transa칞칚o existente"
          },
          "response": []
        },
        {
          "name": "Delete Transaction",
          "request": {
            "method": "DELETE",
            "header": [],
            "url": {
              "raw": "{{base_url}}/transactions/:id",
              "host": ["{{base_url}}"],
              "path": ["transactions", ":id"],
              "variable": [
                {
                  "key": "id",
                  "value": "{{transaction_id}}"
                }
              ]
            },
            "description": "Deleta uma transa칞칚o"
          },
          "response": []
        }
      ]
    },
    {
      "name": "Goals",
      "item": [
        {
          "name": "List Goals",
          "request": {
            "method": "GET",
            "header": [],
            "url": {
              "raw": "{{base_url}}/goals",
              "host": ["{{base_url}}"],
              "path": ["goals"]
            },
            "description": "Lista todas as metas do usu치rio"
          },
          "response": []
        },
        {
          "name": "Get Goal",
          "request": {
            "method": "GET",
            "header": [],
            "url": {
              "raw": "{{base_url}}/goals/:id",
              "host": ["{{base_url}}"],
              "path": ["goals", ":id"],
              "variable": [
                {
                  "key": "id",
                  "value": "{{goal_id}}"
                }
              ]
            },
            "description": "Retorna uma meta espec칤fica"
          },
          "response": []
        },
        {
          "name": "Create Goal",
          "event": [
            {
              "listen": "test",
              "script": {
                "exec": [
                  "if (pm.response.code === 200) {",
                  "    var jsonData = pm.response.json();",
                  "    pm.collectionVariables.set(\"goal_id\", jsonData.id);",
                  "}"
                ]
              }
            }
          ],
          "request": {
            "method": "POST",
            "header": [
              {
                "key": "Content-Type",
                "value": "application/json"
              }
            ],
            "body": {
              "mode": "raw",
              "raw": "{\n  \"title\": \"Viagem para Europa\",\n  \"targetAmount\": 15000.00,\n  \"currentAmount\": 2000.00,\n  \"category\": \"Viagem\",\n  \"deadline\": \"2026-06-30T23:59:59.000Z\"\n}"
            },
            "url": {
              "raw": "{{base_url}}/goals",
              "host": ["{{base_url}}"],
              "path": ["goals"]
            },
            "description": "Cria uma nova meta"
          },
          "response": []
        },
        {
          "name": "Update Goal",
          "request": {
            "method": "PUT",
            "header": [
              {
                "key": "Content-Type",
                "value": "application/json"
              }
            ],
            "body": {
              "mode": "raw",
              "raw": "{\n  \"title\": \"Viagem para Europa (Ver칚o 2026)\",\n  \"targetAmount\": 18000.00,\n  \"deadline\": \"2026-07-15T23:59:59.000Z\"\n}"
            },
            "url": {
              "raw": "{{base_url}}/goals/:id",
              "host": ["{{base_url}}"],
              "path": ["goals", ":id"],
              "variable": [
                {
                  "key": "id",
                  "value": "{{goal_id}}"
                }
              ]
            },
            "description": "Atualiza uma meta existente"
          },
          "response": []
        },
        {
          "name": "Contribute to Goal",
          "request": {
            "method": "POST",
            "header": [
              {
                "key": "Content-Type",
                "value": "application/json"
              }
            ],
            "body": {
              "mode": "raw",
              "raw": "{\n  \"amount\": 500.00\n}"
            },
            "url": {
              "raw": "{{base_url}}/goals/:id/contribute",
              "host": ["{{base_url}}"],
              "path": ["goals", ":id", "contribute"],
              "variable": [
                {
                  "key": "id",
                  "value": "{{goal_id}}"
                }
              ]
            },
            "description": "Adiciona uma contribui칞칚o para a meta"
          },
          "response": []
        },
        {
          "name": "Delete Goal",
          "request": {
            "method": "DELETE",
            "header": [],
            "url": {
              "raw": "{{base_url}}/goals/:id",
              "host": ["{{base_url}}"],
              "path": ["goals", ":id"],
              "variable": [
                {
                  "key": "id",
                  "value": "{{goal_id}}"
                }
              ]
            },
            "description": "Deleta uma meta"
          },
          "response": []
        }
      ]
    },
    {
      "name": "Friends",
      "item": [
        {
          "name": "List Friends",
          "request": {
            "method": "GET",
            "header": [],
            "url": {
              "raw": "{{base_url}}/friends",
              "host": ["{{base_url}}"],
              "path": ["friends"]
            },
            "description": "Lista todos os amigos do usu치rio"
          },
          "response": []
        },
        {
          "name": "Add Friend (Send Invite)",
          "event": [
            {
              "listen": "test",
              "script": {
                "exec": [
                  "if (pm.response.code === 200) {",
                  "    var jsonData = pm.response.json();",
                  "    pm.collectionVariables.set(\"invite_id\", jsonData.id);",
                  "}"
                ]
              }
            }
          ],
          "request": {
            "method": "POST",
            "header": [
              {
                "key": "Content-Type",
                "value": "application/json"
              }
            ],
            "body": {
              "mode": "raw",
              "raw": "{\n  \"username\": \"mariasilva\"\n}"
            },
            "url": {
              "raw": "{{base_url}}/friends/add",
              "host": ["{{base_url}}"],
              "path": ["friends", "add"]
            },
            "description": "Envia convite de amizade para outro usu치rio"
          },
          "response": []
        },
        {
          "name": "Remove Friend",
          "request": {
            "method": "DELETE",
            "header": [],
            "url": {
              "raw": "{{base_url}}/friends/:friendId",
              "host": ["{{base_url}}"],
              "path": ["friends", ":friendId"],
              "variable": [
                {
                  "key": "friendId",
                  "value": "{{friend_id}}"
                }
              ]
            },
            "description": "Remove um amigo (deleta amizade bidirecional)"
          },
          "response": []
        },
        {
          "name": "List Friend Invites",
          "request": {
            "method": "GET",
            "header": [],
            "url": {
              "raw": "{{base_url}}/friends/invites",
              "host": ["{{base_url}}"],
              "path": ["friends", "invites"]
            },
            "description": "Lista convites de amizade recebidos (pendentes)"
          },
          "response": []
        },
        {
          "name": "Accept Friend Invite",
          "request": {
            "method": "POST",
            "header": [],
            "url": {
              "raw": "{{base_url}}/friends/invites/:inviteId/accept",
              "host": ["{{base_url}}"],
              "path": ["friends", "invites", ":inviteId", "accept"],
              "variable": [
                {
                  "key": "inviteId",
                  "value": "{{invite_id}}"
                }
              ]
            },
            "description": "Aceita convite de amizade"
          },
          "response": []
        },
        {
          "name": "Decline Friend Invite",
          "request": {
            "method": "POST",
            "header": [],
            "url": {
              "raw": "{{base_url}}/friends/invites/:inviteId/decline",
              "host": ["{{base_url}}"],
              "path": ["friends", "invites", ":inviteId", "decline"],
              "variable": [
                {
                  "key": "inviteId",
                  "value": "{{invite_id}}"
                }
              ]
            },
            "description": "Recusa convite de amizade"
          },
          "response": []
        }
      ]
    }
  ]
}